mbm/__init__.py
mbm/__main__.py
mbm/aaryan/__init__.py
mbm/aaryan/ast.py
mbm/aaryan/interpreter.py
mbm/aaryan/lexer.py
mbm/aaryan/parser.py
mbm/aaryan/repl.py
mbm/ai/__init__.py
mbm/ai/assistant.py
mbm/ai/nlp.py
mbm/ai/response.py
mbm/assets/README.md
mbm/assets/banners/aaryan.txt
mbm/assets/banners/mbm.txt
mbm/cli/__init__.py
mbm/cli/main.py
mbm/cli/shortcuts.py
mbm/cli/commands/__init__.py
mbm/cli/commands/aaryan.py
mbm/cli/commands/ai.py
mbm/cli/commands/blast.py
mbm/cli/commands/people.py
mbm/cli/commands/student_birthday.py
mbm/core/__init__.py
mbm/core/config.py
mbm/core/constants.py
mbm/core/exceptions.py
mbm/people/__init__.py
mbm/people/models.py
mbm/people/registry.py
mbm/people/data/__init__.py
mbm/people/data/faculty.py
mbm/people/data/student_database.py
mbm/people/data/students.py
mbm/services/__init__.py
mbm/services/wikimedia.py
mbm/services/wikipedia.py
mbm/utils/__init__.py
mbm/utils/animations.py
mbm/utils/birthday.py
mbm/utils/media.py
mbm/utils/platform.py
mbm-0.1.0.dist-info/licenses/LICENSE
mbm-0.1.0.dist-info/METADATA
mbm-0.1.0.dist-info/WHEEL
mbm-0.1.0.dist-info/entry_points.txt
mbm-0.1.0.dist-info/top_level.txt
mbm-0.1.0.dist-info/RECORD
