Metadata-Version: 2.4
Name: mbm
Version: 0.1.0
Summary: MBM - A modular CLI platform with Aaryan language support and AI assistant
Author-email: MBM Team <contact@mbm.edu>
Maintainer-email: MBM Team <contact@mbm.edu>
License: MIT
Project-URL: Homepage, https://github.com/mbm/mbm-cli
Project-URL: Documentation, https://mbm.readthedocs.io
Project-URL: Repository, https://github.com/mbm/mbm-cli
Project-URL: Issues, https://github.com/mbm/mbm-cli/issues
Project-URL: Changelog, https://github.com/mbm/mbm-cli/blob/main/CHANGELOG.md
Keywords: cli,mbm,aaryan,programming-language,ai-assistant,nlp,educational,birthday,countdown
Classifier: Development Status :: 4 - Beta
Classifier: Environment :: Console
Classifier: Intended Audience :: Developers
Classifier: Intended Audience :: Education
Classifier: License :: OSI Approved :: MIT License
Classifier: Operating System :: OS Independent
Classifier: Operating System :: Microsoft :: Windows
Classifier: Operating System :: POSIX :: Linux
Classifier: Operating System :: MacOS :: MacOS X
Classifier: Programming Language :: Python :: 3
Classifier: Programming Language :: Python :: 3.9
Classifier: Programming Language :: Python :: 3.10
Classifier: Programming Language :: Python :: 3.11
Classifier: Programming Language :: Python :: 3.12
Classifier: Programming Language :: Python :: 3.13
Classifier: Topic :: Education
Classifier: Topic :: Software Development :: Interpreters
Classifier: Topic :: Utilities
Requires-Python: >=3.9
License-File: LICENSE
Requires-Dist: click>=8.1.0
Requires-Dist: rich>=13.0.0
Requires-Dist: requests>=2.28.0
Requires-Dist: pydantic>=2.0.0
Requires-Dist: platformdirs>=3.0.0
Provides-Extra: dev
Requires-Dist: pytest>=7.0.0; extra == "dev"
Requires-Dist: pytest-cov>=4.0.0; extra == "dev"
Requires-Dist: black>=23.0.0; extra == "dev"
Requires-Dist: isort>=5.12.0; extra == "dev"
Requires-Dist: mypy>=1.0.0; extra == "dev"
Requires-Dist: ruff>=0.1.0; extra == "dev"
Provides-Extra: nlp
Requires-Dist: spacy>=3.5.0; extra == "nlp"
Provides-Extra: all
Requires-Dist: spacy>=3.5.0; extra == "all"
Dynamic: license-file
